LICENSE.txt
MANIFEST.in
README.md
VERSION
pyproject.toml
py_qgis_wps.egg-info/PKG-INFO
py_qgis_wps.egg-info/SOURCES.txt
py_qgis_wps.egg-info/dependency_links.txt
py_qgis_wps.egg-info/entry_points.txt
py_qgis_wps.egg-info/requires.txt
py_qgis_wps.egg-info/top_level.txt
pyqgisservercontrib/core/__init__.py
pyqgisservercontrib/core/componentmanager.py
pyqgisservercontrib/core/filters.py
pyqgisservercontrib/core/watchfiles.py
pyqgisservercontrib/lizmapacl/__init__.py
pyqgisservercontrib/lizmapacl/filters.py
pyqgiswps/__init__.py
pyqgiswps/accesspolicy.py
pyqgiswps/build.manifest
pyqgiswps/config.py
pyqgiswps/dependencies.py
pyqgiswps/exceptions.py
pyqgiswps/healthcheck.py
pyqgiswps/logger.py
pyqgiswps/middleware.py
pyqgiswps/protos.py
pyqgiswps/runtime.py
pyqgiswps/tests.py
pyqgiswps/version.py
pyqgiswps/wpsserver.py
pyqgiswps/app/__init__.py
pyqgiswps/app/common.py
pyqgiswps/app/process.py
pyqgiswps/app/request.py
pyqgiswps/app/service.py
pyqgiswps/executors/__init__.py
pyqgiswps/executors/logstore.py
pyqgiswps/executors/processfactory.py
pyqgiswps/executors/processingcontext.py
pyqgiswps/executors/processingexecutor.py
pyqgiswps/executors/processingio.py
pyqgiswps/executors/processingprocess.py
pyqgiswps/executors/io/datetimeio.py
pyqgiswps/executors/io/filesio.py
pyqgiswps/executors/io/geometryio.py
pyqgiswps/executors/io/layersio.py
pyqgiswps/handlers/__init__.py
pyqgiswps/handlers/basehandler.py
pyqgiswps/handlers/oapihandler.py
pyqgiswps/handlers/owshandler.py
pyqgiswps/handlers/processeshandler.py
pyqgiswps/handlers/roothandler.py
pyqgiswps/handlers/statushandler.py
pyqgiswps/handlers/storehandler.py
pyqgiswps/html/__init__.py
pyqgiswps/html/dashboard.css
pyqgiswps/html/dashboard.html
pyqgiswps/html/dashboard.js
pyqgiswps/html/details.html
pyqgiswps/html/icons.css
pyqgiswps/html/jquery.slim.min.js
pyqgiswps/html/assets/popper.min.js
pyqgiswps/html/bootstrap/css/bootstrap-grid.css
pyqgiswps/html/bootstrap/css/bootstrap-grid.css.map
pyqgiswps/html/bootstrap/css/bootstrap-grid.min.css
pyqgiswps/html/bootstrap/css/bootstrap-grid.min.css.map
pyqgiswps/html/bootstrap/css/bootstrap-reboot.css
pyqgiswps/html/bootstrap/css/bootstrap-reboot.css.map
