Metadata-Version: 2.4
Name: py-qgis-wps
Version: 1.9.1
Summary: Py-Qgis-WPS is an implementation of the Web Processing Service standard from the Open Geospatial Consortium
Author-email: 3Liz <david.marteau@3liz.com>
Maintainer-email: David Marteau <david.marteau@3liz.com>
Project-URL: Homepage, https://gitthub.com/3liz/py-qgis-server
Project-URL: Repository, https://github.com/3liz/py-qgis-server.git
Project-URL: Documentation, https://docs.3liz.org/py-qgis-server
Classifier: Environment :: Web Environment
Classifier: Intended Audience :: Developers
Classifier: Intended Audience :: Science/Research
Classifier: Programming Language :: Python :: 3 :: Only
Classifier: Programming Language :: Python :: 3.10
Classifier: Programming Language :: Python :: 3.11
Classifier: Programming Language :: Python :: 3.12
Classifier: Operating System :: POSIX :: Linux
Classifier: Topic :: Scientific/Engineering :: GIS
Classifier: License :: OSI Approved :: Mozilla Public License 2.0 (MPL 2.0)
Requires-Python: >=3.10
License-File: LICENSE.txt
Requires-Dist: tornado>=6
Requires-Dist: pyzmq>=17
Requires-Dist: PyYAML
Requires-Dist: OWSLib
Requires-Dist: psutil
Requires-Dist: redis
Requires-Dist: typing-extensions
Dynamic: license-file
